{
  "styleId": "A3381_999",
  "name": "A3381_999_Purse",
  "program": 5669,
  "programName": "Seasonal Recycled Tech Fabric",
  "material": "100% Recycled Polyester Lining: 100% Recycled PL",
  "groupId": "drop-1",
  "colorNames": "Multicolour",
  "colorId": 999,
  "filters": ["acc1"],
  "responsible": true,
  "weight": 4010,
  "wholesalePriceDKK": 200,
  "wholesalePriceEUR": 30,
  "wholesalePriceUSD": 36,
  "wholesalePriceGBP": 26,
  "retailPriceDKK": 499,
  "retailPriceEUR": 75,
  "retailPriceUSD": 85,
  "retailPriceGBP": 65
}