{"styleId":"F6313_252","name":"F6313_252_Pants","program":6313,"programName":"Lightweight Stripe","material":"75% Rayon 25% Polyamide","groupId":"drop-2","colorNames":"Phantom","colorId":252,"filters":["rtw9"],"responsible":true,"weight":2850,"wholesalePriceDKK":535,"wholesalePriceEUR":77,"wholesalePriceUSD":103,"wholesalePriceGBP":70,"retailPriceDKK":1499,"retailPriceEUR":215,"retailPriceUSD":245,"retailPriceGBP":195,"re-runner":false,"assets":["https://res.cloudinary.com/dd6fpxydm/image/upload/v1612095338/AW21_21.3/21.3_PACKSHOTS/F6313_6313_252.jpg"]}