{"styleId":"F6735_099","name":"F6735_099_Midi Dress","program":6403,"programName":"Dotted Georgette","material":"100% Recycled Polyester","groupId":"drop-1","colorNames":"Black","colorId":99,"filters":["rtw1"],"responsible":true,"weight":4306946,"sizeRange":"XXS/XS, S/M, L/XL","chest":140,"waist":0,"hip":0,"bottomWidth":140,"totalLenght":115,"inseamLenght":0,"sleeveLenght":51,"height":0,"length":0,"width":0,"heelHeight":0,"wholesalePriceDKK":607,"wholesalePriceEUR":88,"wholesalePriceUSD":119,"wholesalePriceGBP":77,"retailPriceDKK":1699,"retailPriceEUR":245,"retailPriceUSD":285,"retailPriceGBP":77,"retailRMB":2295,"assets":[],"re-runner":true}