{"styleId":"A3958_721","name":"A3958_721_Socks","program":5757,"programName":"Lurex Blend","material":"65% Polyamide 21% Cotton 12% Polyester 2% Elastane","groupId":"drop-1","colorNames":"Heliotrope","colorId":721,"filters":["acc1"],"responsible":false,"weight":4106109,"sizeRange":"XS/S, M/L","chest":0,"waist":0,"hip":0,"bottomWidth":0,"totalLength":0,"inseamLength":0,"sleeveLength":0,"height":0,"length":0,"width":0,"heelHeight":0,"wholesalePriceDKK":120,"wholesalePriceEUR":18,"wholesalePriceUSD":21,"wholesalePriceGBP":16,"retailPriceDKK":299,"retailPriceEUR":45,"retailPriceUSD":50,"retailPriceGBP":16,"retailRMB":395,"assets":[],"re-runner":true}