{
  "waist": 0,
  "retailPriceUSD": 185,
  "chest": 0,
  "assets": [],
  "retailRMB": 1495,
  "program": 6099,
  "colorNames": "Bright White",
  "width": 0,
  "length": 0,
  "height": 0,
  "material": "100% Organic Cotton",
  "inseamLength": 0,
  "re-runner": true,
  "wholesalePriceGBP": 52,
  "totalLength": 0,
  "heelHeight": 0,
  "name": "F5778_151_Shirt",
  "styleId": "F5778_151",
  "sleeveLength": 0,
  "retailPriceGBP": 52,
  "programName": "Cotton Poplin",
  "hip": 0,
  "responsible": true,
  "wholesalePriceEUR": 56,
  "weight": 4306490,
  "wholesalePriceDKK": 393,
  "groupId": "drop-1",
  "wholesalePriceUSD": 78,
  "bottomWidth": 0,
  "filters": [
    "rtw13",
    "rtw14",
    "misc4"
  ],
  "sizeRange": "32, 34, 36, 38, 40, 42, 44",
  "retailPriceEUR": 155,
  "retailPriceDKK": 1099,
  "colorId": 151
}