{
  "retailPriceUSD": 245,
  "assets": [],
  "program": 6304,
  "colorNames": "Black",
  "material": "70% Recycled Wool 24% Polyamide 6% Viscose",
  "re-runner": false,
  "wholesalePriceGBP": 78,
  "name": "F6184_99_Skirt",
  "styleId": "F6184_99",
  "retailPriceGBP": 195,
  "programName": "Multi Wool",
  "responsible": true,
  "wholesalePriceEUR": 86,
  "weight": 2890,
  "wholesalePriceDKK": 600,
  "groupId": "drop-2",
  "wholesalePriceUSD": 103,
  "filters": [
    "rtw6",
    "misc2"
  ],
  "retailPriceEUR": 215,
  "retailPriceDKK": 1499,
  "colorId": 99
}