{
  "retailPriceUSD": 195,
  "assets": [],
  "program": 5719,
  "colorNames": "Black",
  "material": "100% Recycled Polyester",
  "re-runner": false,
  "wholesalePriceGBP": 62,
  "name": "A3602_99_knot_Purse",
  "styleId": "A3602_99",
  "retailPriceGBP": 155,
  "programName": "Knot",
  "responsible": true,
  "wholesalePriceEUR": 70,
  "weight": 1750,
  "wholesalePriceDKK": 480,
  "groupId": "drop-2",
  "wholesalePriceUSD": 86,
  "filters": [
    "acc1",
    "acc2"
  ],
  "retailPriceEUR": 175,
  "retailPriceDKK": 1199,
  "colorId": 99
}